kanit
