Metadata-Version: 1.0
Name: kanit
Version: 0.7
Summary: Kanit kanban tool
Home-page: https://github.com/LazarusID/kanit
Author: Clay Dowling
Author-email: clay@lazarusid.com
License: BSD
Platform: UNKNOWN
